mailez/__init__.py
mailez/main.py
mailez-1.0.4.dist-info/METADATA
mailez-1.0.4.dist-info/WHEEL
mailez-1.0.4.dist-info/top_level.txt
mailez-1.0.4.dist-info/RECORD
