Metadata-Version: 2.1
Name: mailez
Version: 1.0.4
Summary: Mass mail sender with custom tweaks
Author: Mehmet Utku OZTURK
Author-email: <thejupyter@gmail.com>
Keywords: email,mail
Classifier: Development Status :: 3 - Alpha
Classifier: Intended Audience :: Developers
Classifier: Natural Language :: English
Classifier: Programming Language :: Python :: 3
Requires-Dist: pandas
